enkanetwork/__init__.py
enkanetwork/assets.py
enkanetwork/cache.py
enkanetwork/client.py
enkanetwork/config.py
enkanetwork/enum.py
enkanetwork/exception.py
enkanetwork/http.py
enkanetwork/tools.py
enkanetwork/utils.py
enkanetwork/assets/data/artifact_props.json
enkanetwork/assets/data/artifacts.json
enkanetwork/assets/data/characters.json
enkanetwork/assets/data/constellations.json
enkanetwork/assets/data/costumes.json
enkanetwork/assets/data/fight_props.json
enkanetwork/assets/data/namecards.json
enkanetwork/assets/data/pfps.json
enkanetwork/assets/data/skills.json
enkanetwork/assets/data/weapons.json
enkanetwork/assets/langs/artifact_sets.json
enkanetwork/assets/langs/artifacts.json
enkanetwork/assets/langs/characters.json
enkanetwork/assets/langs/constellations.json
enkanetwork/assets/langs/fight_props.json
enkanetwork/assets/langs/namecards.json
enkanetwork/assets/langs/skills.json
enkanetwork/assets/langs/weapons.json
enkanetwork/enkanetwork_update/__init__.py
enkanetwork/enkanetwork_update/config.py
enkanetwork/enkanetwork_update/enka_update.py
enkanetwork/enkanetwork_update/pathfinding.py
enkanetwork/enkanetwork_update/__pycache__/__init__.cpython-312.pyc
enkanetwork/enkanetwork_update/__pycache__/config.cpython-312.pyc
enkanetwork/enkanetwork_update/__pycache__/enka_update.cpython-312.pyc
enkanetwork/enkanetwork_update/__pycache__/pathfinding.cpython-312.pyc
enkanetwork/model/__init__.py
enkanetwork/model/assets.py
enkanetwork/model/base.py
enkanetwork/model/build.py
enkanetwork/model/character.py
enkanetwork/model/equipments.py
enkanetwork/model/hoyos.py
enkanetwork/model/players.py
enkanetwork/model/profile.py
enkanetwork/model/stats.py
enkanetwork/model/utils.py
enkanetwork/types/__init__.py
enkanetwork/types/enkanetwork.py
enkanetwork/types/__pycache__/__init__.cpython-312.pyc
enkanetworkv2.py-2.1.5.dist-info/LICENSE
enkanetworkv2.py-2.1.5.dist-info/METADATA
enkanetworkv2.py-2.1.5.dist-info/WHEEL
enkanetworkv2.py-2.1.5.dist-info/top_level.txt
enkanetworkv2.py-2.1.5.dist-info/RECORD
