Metadata-Version: 2.1
Name: enkanetworkv2.py
Version: 2.1.5
Summary: Library for fetching JSON data from site https://enka.network/
Home-page: https://github.com/DEViantUA/EnkaNetworkV2.py
Author: DeviantUa
Author-email: deviantapi@gmail.com
Keywords: enkanetwork.py,enkanetwork,enka.network,genshinapi,enkanetworkV2,enkanetworkV2.py
Classifier: Programming Language :: Python :: 3
Classifier: License :: OSI Approved :: MIT License
Classifier: Operating System :: OS Independent
Requires-Python: >=3.6
License-File: LICENSE
Requires-Dist: pydantic
Requires-Dist: aiohttp
Requires-Dist: cachetools
